[
  {
    "androidPermissionNames": [
      "android.permission.ACCESS_FINE_LOCATION",
      "android.permission.ACCESS_COARSE_LOCATION"
    ],
    "showPermissionName": "定位 GPS定位，WIFI定位",
    "permissionAimDescription": "用于新闻下微站展示,自动定位区县栏目展示场景"
  },
  {
    "androidPermissionNames": [
      "android.permission.WRITE_EXTERNAL_STORAGE",
      "android.permission.READ_EXTERNAL_STORAGE"
    ],
    "showPermissionName": "内存读，写",
    "permissionAimDescription": "用于APP写入/下载/保存/读取图片、文件等信息"
  },
  {
    "androidPermissionNames": [
      "android.permission.CAMERA"
    ],
    "showPermissionName": "访问摄像头",
    "permissionAimDescription": "用于拍照、录制视频、扫一扫AR识别等场景"
  },
  {
    "androidPermissionNames": [
      "android.permission.RECORD_AUDIO"
    ],
    "showPermissionName": "录音功能",
    "permissionAimDescription": "通过手机和耳机的麦克 用于录音、语音检索等场景"
  },
  {
    "androidPermissionNames": [
      "android.permission.READ_CONTACTS"
    ],
    "showPermissionName": "读取联系人",
    "permissionAimDescription": "测试功能"
  }

]